[{"src":"https://github.com/hrsh7th/nvim-cmp","name":"nvim-cmp"},{"src":"https://github.com/lewis6991/gitsigns.nvim","name":"gitsigns.nvim"},{"src":"https://github.com/numToStr/Comment.nvim","name":"Comment.nvim"},{"src":"https://github.com/scalameta/nvim-metals","name":"nvim-metals"},{"src":"https://github.com/stevearc/conform.nvim","name":"conform.nvim"},{"src":"https://github.com/nvim-lua/plenary.nvim","name":"plenary.nvim"},{"src":"https://github.com/stevearc/oil.nvim","name":"oil.nvim"},{"src":"https://github.com/kylechui/nvim-surround","name":"nvim-surround"},{"src":"https://github.com/ggandor/leap.nvim","name":"leap.nvim"},{"src":"https://github.com/tpope/vim-sleuth","name":"vim-sleuth"},{"src":"https://github.com/uga-rosa/ccc.nvim","name":"ccc.nvim"},{"src":"https://github.com/junegunn/vim-easy-align","name":"vim-easy-align"},{"src":"https://github.com/stevearc/quicker.nvim","name":"quicker.nvim"},{"src":"https://github.com/j-morano/buffer_manager.nvim","name":"buffer_manager.nvim"},{"src":"https://github.com/chomosuke/typst-preview.nvim","name":"typst-preview.nvim"},{"src":"https://github.com/windwp/nvim-autopairs","name":"nvim-autopairs"},{"src":"https://github.com/echasnovski/mini.pick","name":"mini.pick"},{"version":"main","src":"https://github.com/nvim-treesitter/nvim-treesitter","name":"nvim-treesitter"},{"version":"main","src":"https://github.com/nvim-treesitter/nvim-treesitter-textobjects","name":"nvim-treesitter-textobjects"},{"src":"https://github.com/windwp/nvim-ts-autotag","name":"nvim-ts-autotag"},{"src":"https://github.com/rebelot/kanagawa.nvim","name":"kanagawa.nvim"},{"src":"https://github.com/kyazdani42/nvim-web-devicons","name":"nvim-web-devicons"},{"version":"global-status-line","src":"https://github.com/Avimitin/galaxyline.nvim","name":"galaxyline.nvim"},{"src":"https://github.com/lukas-reineke/indent-blankline.nvim","name":"indent-blankline.nvim"},{"src":"https://github.com/j-hui/fidget.nvim","name":"fidget.nvim"},{"src":"https://github.com/stevearc/dressing.nvim","name":"dressing.nvim"},{"src":"https://github.com/luukvbaal/statuscol.nvim","name":"statuscol.nvim"},{"src":"https://github.com/sphamba/smear-cursor.nvim","name":"smear-cursor.nvim"}]